{
    "apl": 13,
    "authors": [
        "Scott Moore",
        "Cindy Moore"
    ],
    "campaigns": [
        "Forgotten Realms"
    ],
    "code": "CCC-QCC2020-03",
    "date_created": "20201028",
    "full_title": "CCC-QCC2020-03 Run For The Money",
    "hours": "4",
    "is_adventure": true,
    "level_range": "11-16",
    "payWhatYouWant": false,
    "price": 4.99,
    "product_id": "333653",
    "season": null,
    "tiers": 3,
    "title": "Run For The Money",
    "url": "https://www.dmsguild.com/product/333653/?affiliate_id=171040"
}