{
    "apl": 3,
    "authors": [
        "Addy Tortosa"
    ],
    "campaigns": [
        "Forgotten Realms"
    ],
    "code": "SJ-DC-NCH-01",
    "date_created": "20221103",
    "full_title": "SJ-DC-NCH-01 A String of Pearls",
    "hours": "4",
    "is_adventure": true,
    "level_range": null,
    "product_id": "415579",
    "seed": "Create a Location in Wildspace",
    "tiers": 1,
    "title": "A String of Pearls",
    "url": "https://www.dmsguild.com/product/415579/SJDCNCH01-A-String-of-Pearls?filters=0_0_100057_0_0_0_0_0&affiliate_id=171040"
}