{
    "apl": 8,
    "authors": [
        "Teddy Benson",
        "David Sklenicka"
    ],
    "campaigns": [
        "Forgotten Realms"
    ],
    "code": "SJ-DC-DRAGON-04",
    "date_created": "20230926",
    "full_title": "SJ-DC-DRAGON-04 : The Call from Space!",
    "hours": "4",
    "is_adventure": true,
    "level_range": "5-10",
    "payWhatYouWant": false,
    "price": 2.99,
    "product_id": "451471",
    "season": "Spelljammer",
    "seed": "Create a Location in Wildspace",
    "tiers": 2,
    "title": "The Call from Space!",
    "url": "https://www.dmsguild.com/product/451471/?affiliate_id=171040"
}