{
    "apl": 1,
    "authors": [
        "David Morris",
        "MOGC"
    ],
    "campaigns": [
        "Forgotten Realms"
    ],
    "code": "CCC-SALT-01-01",
    "community_content": true,
    "date_created": "20170425",
    "dungeoncraft": false,
    "full_title": "CCC-SALT-01-01 Rumors of Riches",
    "hours": "2",
    "is_adventure": true,
    "level_range": "1-4",
    "payWhatYouWant": false,
    "price": 2.99,
    "product_id": "210440",
    "salvage_mission": false,
    "season": null,
    "tiers": 1,
    "title": "Rumors of Riches",
    "url": "https://www.dmsguild.com/product/210440/?affiliate_id=171040"
}