{
    "apl": 2,
    "authors": [
        "Derek Gray",
        "David Morris",
        "MOGC"
    ],
    "campaigns": [
        "Forgotten Realms"
    ],
    "code": "CCC-SALT-01-03",
    "community_content": true,
    "date_created": "20170425",
    "dungeoncraft": false,
    "full_title": "CCC-SALT-01-03 Broken Halls of Goldahroud",
    "hours": "4",
    "is_adventure": true,
    "level_range": "1-4",
    "payWhatYouWant": false,
    "price": 4.99,
    "product_id": "210444",
    "salvage_mission": false,
    "season": null,
    "tiers": 1,
    "title": "Broken Halls of Goldahroud",
    "url": "https://www.dmsguild.com/product/210444/?affiliate_id=171040"
}