{
    "apl": 12,
    "authors": [
        "Lysa Chen",
        "Ruty Rutenberg"
    ],
    "campaigns": [],
    "code": "DDHC-TOA-10",
    "community_content": false,
    "date_created": "20170908",
    "dungeoncraft": false,
    "full_title": "Ruins of Hisari (DDHC-TOA-10)",
    "hours": "4",
    "is_adventure": true,
    "level_range": "11-16",
    "payWhatYouWant": false,
    "price": 3.99,
    "product_id": "220610",
    "salvage_mission": false,
    "season": null,
    "tiers": 3,
    "title": "Ruins of Hisari (DDHC-TOA-10)",
    "url": "https://www.dmsguild.com/product/220610/?affiliate_id=171040"
}