{
    "apl": 5,
    "authors": [
        "Adrian Arduini"
    ],
    "campaigns": [
        "Forgotten Realms"
    ],
    "code": "CCC-SFBAY-02-02",
    "date_created": "20180821",
    "full_title": "CCC-SFBay-02-02 Rise of the Ogre King",
    "hours": "4",
    "is_adventure": true,
    "level_range": "5-10",
    "payWhatYouWant": false,
    "price": 4.99,
    "product_id": "250384",
    "season": null,
    "tiers": 2,
    "title": "Rise of the Ogre King",
    "url": "https://www.dmsguild.com/product/250384/?affiliate_id=171040"
}