{
    "apl": 1,
    "authors": [
        "Dave Zajac"
    ],
    "campaigns": [
        "Forgotten Realms"
    ],
    "code": "CCC-RCC-01-03",
    "date_created": "20200109",
    "full_title": "CCC-RCC-01-03 Chains of Desperation",
    "hours": "2",
    "is_adventure": true,
    "level_range": "1-4",
    "payWhatYouWant": false,
    "price": 2.99,
    "product_id": "299977",
    "season": null,
    "tiers": 1,
    "title": "Chains of Desperation",
    "url": "https://www.dmsguild.com/product/299977/?affiliate_id=171040"
}