{
    "apl": 2,
    "authors": [
        "Niccolo Estrella",
        "Greasy Snitches"
    ],
    "campaigns": [
        "Forgotten Realms"
    ],
    "code": "DC-POA-GSP03-01",
    "date_created": "20201201",
    "full_title": "The Missing Link (DC-PoA-GSP03-01)",
    "hours": "4",
    "is_adventure": true,
    "level_range": "1-4",
    "price": 4.99,
    "product_id": "337908",
    "season": "Icewind Dale",
    "tiers": 1,
    "title": "The Missing Link DC-PoA-GSP03-01",
    "url": "https://www.dmsguild.com/product/337908/?affiliate_id=171040",
    "seed": "Once Bitten, Ice Shy"
}