{
    "apl": 13,
    "authors": [
        "Christopher Bagg"
    ],
    "campaigns": [
        "Eberron"
    ],
    "code": "EB-SM-CHROME",
    "date_created": "20210608",
    "full_title": "Chrome On The Range",
    "hours": "4",
    "is_adventure": true,
    "last_update": "20260105",
    "level_range": "11-16",
    "payWhatYouWant": false,
    "price": 2.99,
    "product_id": "360228",
    "season": null,
    "tiers": 3,
    "title": "Chrome On The Range",
    "url": "https://www.dmsguild.com/product/360228/?affiliate_id=171040"
}