{
    "apl": 4,
    "authors": [
        "Hugh Lee",
        "Steven Truong"
    ],
    "campaigns": [
        "Forgotten Realms"
    ],
    "code": "DC-POA-TDG01-04",
    "community_content": true,
    "date_created": "20210829",
    "dungeoncraft": true,
    "full_title": "DC-PoA-TDG01-04 Despair In The Family",
    "hours": "4",
    "is_adventure": true,
    "level_range": "1-4",
    "payWhatYouWant": false,
    "price": 2.99,
    "product_id": "369144",
    "salvage_mission": false,
    "season": "10 - Icewind Dale",
    "seed": "The Muttering Gnome",
    "tiers": 1,
    "title": "DC-PoA-TDG01-04 Despair In The Family",
    "url": "https://www.dmsguild.com/product/369144/?affiliate_id=171040"
}