{
    "apl": 1,
    "authors": [
        "Rory Dennison",
        "Brand McMann",
        "Doug Seipel",
        "Ed Stoltman"
    ],
    "campaigns": [
        "Forgotten Realms"
    ],
    "code": "DC-POA-COULEE21-BUNDLE",
    "date_created": "20210830",
    "full_title": "DC-POA-Coulee21-Bundle Legends of the Icewind Dale Snipe Series and VTT Maps",
    "hours": "4",
    "is_adventure": false,
    "level_range": "1-4",
    "payWhatYouWant": false,
    "price": 10.0,
    "product_id": "369292",
    "season": null,
    "tiers": 1,
    "title": "Legends of the Icewind Dale Snipe Series and VTT Maps",
    "url": "https://www.dmsguild.com/product/369292/?affiliate_id=171040"
}