{
    "apl": 13,
    "authors": [
        "Baldman Games",
        "Greg Marks"
    ],
    "campaigns": [
        "Forgotten Realms"
    ],
    "code": "CCC-BMG-MOON18-2",
    "date_created": "20220630",
    "full_title": "CCC-BMG-MOON18-2 What We Reap",
    "hours": "4",
    "is_adventure": true,
    "level_range": "11-16",
    "payWhatYouWant": false,
    "price": 4.99,
    "product_id": "399829",
    "season": null,
    "tiers": 3,
    "title": "What We Reap",
    "url": "https://www.dmsguild.com/product/399829/?affiliate_id=171040"
}