{
    "apl": 8,
    "authors": [
        "Johnny Smith",
        "Triden Games"
    ],
    "campaigns": [
        "Forgotten Realms"
    ],
    "code": "WBW-DC-AUG-01",
    "date_created": "20220823",
    "full_title": "WBW-DC-AUG-01 Last Hour",
    "hours": "4",
    "is_adventure": true,
    "level_range": "5-10",
    "payWhatYouWant": false,
    "price": 4.99,
    "product_id": "407553",
    "season": "The Wild Beyond the Witchlight",
    "seed": "Create a Domain of Delight",
    "tiers": 2,
    "title": "Last Hour",
    "url": "https://www.dmsguild.com/product/407553/?affiliate_id=171040"
}