{
    "apl": 8,
    "authors": [
        "Jonathan Self"
    ],
    "campaigns": [
        "Forgotten Realms"
    ],
    "code": "WBW-DC-DES-01-09",
    "date_created": "20220831",
    "full_title": "Strahd Must Die!",
    "hours": "4",
    "is_adventure": true,
    "level_range": "5-10",
    "payWhatYouWant": false,
    "price": 6.99,
    "product_id": "408602",
    "season": null,
    "tiers": 2,
    "seed": "Create a Domain of Delight",
    "title": "Strahd Must Die!",
    "url": "https://www.dmsguild.com/product/408602/?affiliate_id=171040"
}