{
    "apl": 20,
    "authors": [
        "Integral Game Conglomerate LLC"
    ],
    "campaigns": [
        "Eberron"
    ],
    "code": "EB-SALVAGE-RSM-T4.4",
    "community_content": false,
    "date_created": "20230131",
    "dungeoncraft": false,
    "full_title": "EB-SALVAGE-RSM-T4.4 Daughter of Khyber",
    "hours": "2",
    "is_adventure": true,
    "level_range": "17-20",
    "payWhatYouWant": false,
    "price": 1.0,
    "product_id": "425292",
    "salvage_mission": false,
    "season": "Oracle of War",
    "tiers": 4,
    "title": "Daughter of Khyber",
    "url": "https://www.dmsguild.com/product/425292/?affiliate_id=171040"
}