{
    "apl": 3,
    "authors": [
        "Unite the Factions",
        "Camille G.",
        "Chris D."
    ],
    "campaigns": [
        "Forgotten Realms"
    ],
    "code": "SJ-DC-UNITE-01",
    "date_created": "20231224",
    "full_title": "SJ-DC-UNITE-01 Asteroid Escape",
    "hours": "4",
    "is_adventure": true,
    "level_range": "1-4",
    "payWhatYouWant": false,
    "price": 4.99,
    "product_id": "464119",
    "season": "Spelljammer",
    "tiers": 1,
    "title": "Asteroid Escape",
    "url": "https://www.dmsguild.com/product/464119/?affiliate_id=171040",
    "seed": "Create a Location in Wildspace"
}