{
    "apl": 13,
    "authors": [
        "Pauline Feraren"
    ],
    "campaigns": [
        "Forgotten Realms"
    ],
    "code": "FR-DC-IMP-01",
    "date_created": "20240331",
    "full_title": "Blood Price (FR-DC-IMP-01)",
    "hours": "4",
    "is_adventure": true,
    "level_range": "11-16",
    "payWhatYouWant": false,
    "price": 4.99,
    "product_id": "476113",
    "season": null,
    "tiers": 3,
    "title": "Blood Price",
    "url": "https://www.dmsguild.com/product/476113/?affiliate_id=171040"
}