{
    "apl": null,
    "authors": [
        "Steve Hill"
    ],
    "campaigns": [
        "Forgotten Realms"
    ],
    "code": "PS-DC-PUB-05",
    "community_content": true,
    "date_created": "20250720",
    "dungeoncraft": true,
    "full_title": "PS-DC-PUB-05 Planar Pub Crawl: Nights to Remember",
    "hours": "2",
    "is_adventure": false,
    "last_update": "20260104",
    "level_range": null,
    "payWhatYouWant": false,
    "price": 5.0,
    "product_id": "530335",
    "salvage_mission": false,
    "season": "13 - Planescape",
    "tiers": null,
    "title": "Planar Pub Crawl: Nights to Remember",
    "url": "https://www.dmsguild.com/product/530335/?affiliate_id=171040"
}