{
    "apl": null,
    "authors": [
        "Dungeon Masters Guild"
    ],
    "campaigns": [
        "Forgotten Realms"
    ],
    "code": "FR-DC-CGB-01",
    "date_created": "20250904",
    "full_title": "FR-DC-CGB-01 Chaotic Good Brewing Dragon Con 2025 Bundle [BUNDLE]",
    "hours": null,
    "is_adventure": false,
    "last_update": "20250907",
    "level_range": null,
    "payWhatYouWant": false,
    "price": 14.97,
    "product_id": "535799",
    "season": null,
    "tiers": null,
    "title": "Chaotic Good Brewing Dragon Con 2025 Bundle [BUNDLE]",
    "url": "https://www.dmsguild.com/product/535799/?affiliate_id=171040"
}