{
    "apl": 1,
    "authors": [
        "Keith Christensen",
        "Lindsey Ginou"
    ],
    "campaigns": [
        "Forgotten Realms"
    ],
    "code": "CCC-AN-01",
    "date_created": "20190102",
    "full_title": "CCC-AN-01 Secrets of Golden Fire",
    "hours": "4",
    "is_adventure": true,
    "level_range": "1-4",
    "price": null,
    "product_id": "263173",
    "season": null,
    "tiers": 1,
    "title": "CCC-AN-01 Secrets of Golden Fire",
    "url": "https://www.dmsguild.com/product/263173/?affiliate_id=171040"
}