{
    "apl": 3,
    "authors": [
        "Christopher B. Bertucio"
    ],
    "campaigns": [
        "Forgotten Realms"
    ],
    "code": "DC-POA-CBB-01",
    "date_created": "20210103",
    "full_title": "DC-POA-CBB-01 : Twirling Towards Oblivion",
    "hours": "4",
    "is_adventure": true,
    "level_range": "1-4",
    "price": 3.99,
    "product_id": "342209",
    "tiers": 1,
    "title": "DC-POA-CBB-01  Twirling Towards Oblivion",
    "url": "https://www.dmsguild.com/product/342209/?affiliate_id=171040"
}