{
    "apl": null,
    "authors": [
        "Andy Dempz",
        "Gamehole Con"
    ],
    "campaigns": [
        "Forgotten Realms"
    ],
    "code": "PO-BK-02-10",
    "date_created": "20230414",
    "full_title": "PO-BK-02-10 A Grim and Ravenous Arrival",
    "hours": "2",
    "is_adventure": true,
    "level_range": "1",
    "price": null,
    "product_id": "433917",
    "season": null,
    "tiers": null,
    "title": "PO-BK-02-10 A Grim and Ravenous Arrival",
    "url": "https://www.dmsguild.com/product/433917/?affiliate_id=171040"
}