{
    "apl": 2,
    "authors": [],
    "campaign": null,
    "code": null,
    "date_created": "20250714",
    "full_title": "Rising Shadows Trilogy 6: Earthmother's Eye Trilogy [BUNDLE]",
    "hours": 4,
    "is_adventure": false,
    "level_range": null,
    "price": null,
    "product_id": "529671",
    "tiers": 2,
    "title": "Rising Shadows Trilogy 6 Earthmother's Eye Trilogy [BUNDLE]",
    "url": "https://www.dmsguild.com/product/529671/Rising-Shadows-Trilogy-6-Earthmothers-Eye-Trilogy-BUNDLE?affiliate_id=171040&filters=45470_0_0_0_0_0_0_0_0"
}