{
    "ai_content": false,
    "apl": null,
    "authors": [],
    "campaigns": [
        "Forgotten Realms"
    ],
    "code": null,
    "community_content": false,
    "date_created": null,
    "dungeoncraft": false,
    "full_title": "Adventure Atlas: The Mortuary",
    "hours": null,
    "is_adventure": true,
    "last_update": "20260702",
    "level_range": null,
    "payWhatYouWant": false,
    "price": null,
    "product_id": "SRC-00125",
    "salvage_mission": false,
    "season": null,
    "tiers": null,
    "title": "Adventure Atlas: The Mortuary",
    "url": "https://marketplace.dndbeyond.com/category/SRC-00125"
}
