{
    "apl": null,
    "authors": [
        "Bryan Mets"
    ],
    "campaign": "Forgotten Realms",
    "code": "WBW-DC-PUFF-01",
    "date_created": "20250602",
    "full_title": "WBW-DC-PUFF-01 Puffalo's Proposal",
    "hours": "1",
    "is_adventure": true,
    "level_range": "1",
    "product_id": "WBW-DC-PUFF-01-Puffalos-Proposal",
    "tiers": null,
    "title": "Puffalo's Proposal",
    "url": "https://www.dmsguild.com/product/524648/WBWDCPUFF01-Puffalos-Proposal?filters=45470_0_0_0_0_0"
}